salt_tower/__init__.py
salt_tower/loader.py
salt_tower/pillar/__init__.py
salt_tower/pillar/tower.py
salt_tower/renderers/__init__.py
salt_tower/renderers/filter.py
salt_tower/renderers/text.py
salt_tower/renderers/yamlet.py
test/__init__.py
test/conftest.py
test/fixtures/pillar/data.yaml
test/master.yml
test/pillar/__init__.py
test/pillar/test_tower.py
test/pillar/test_tower_tower.py
test/renderers/__init__.py
test/renderers/test_filter.py
test/renderers/test_text.py
test/renderers/test_yamlet.py
salt_tower-1.12.0.dist-info/entry_points.txt
salt_tower-1.12.0.dist-info/WHEEL
salt_tower-1.12.0.dist-info/METADATA
salt_tower-1.12.0.dist-info/licenses/LICENSE
salt_tower-1.12.0.dist-info/RECORD
