Metadata-Version: 2.1
Name: salt-tower
Version: 1.12.0
Summary: A Flexible External Salt Pillar Module
License: MIT
Author-email: Jan Graichen <jgraichen@altimos.de>
Requires-Python: >=3.8.2,<4.0
Classifier: Development Status :: 5 - Production/Stable
Classifier: Environment :: Plugins
Classifier: Intended Audience :: System Administrators
Classifier: License :: OSI Approved :: MIT License
Classifier: Programming Language :: Python :: 3
Classifier: Topic :: System :: Systems Administration
Requires-Dist: salt
Provides-Extra: docs
Requires-Dist: mike~=1.1.2; extra == "docs"
Requires-Dist: mkdocs-awesome-pages-plugin~=2.8.0; extra == "docs"
Requires-Dist: mkdocs-git-revision-date-plugin~=0.3.2; extra == "docs"
Requires-Dist: mkdocs-material~=9.0.12; extra == "docs"
Requires-Dist: setuptools; extra == "docs"
Provides-Extra: test
Requires-Dist: pylint~=2.16.1; extra == "test"
Requires-Dist: pytest~=7.2.1; extra == "test"
Project-URL: homepage, https://github.com/jgraichen/salt-tower
